{"trial_id": "0037", "hyperparameters": {"space": [{"class_name": "Int", "config": {"name": "1st_layer", "default": null, "conditions": [], "min_value": 128, "max_value": 320, "step": 32, "sampling": "linear"}}, {"class_name": "Int", "config": {"name": "2nd_layer", "default": null, "conditions": [], "min_value": 128, "max_value": 320, "step": 32, "sampling": "linear"}}, {"class_name": "Choice", "config": {"name": "learning_rate", "default": 0.001, "conditions": [], "values": [0.001, 0.01, 0.001, 0.0001], "ordered": true}}], "values": {"1st_layer": 320, "2nd_layer": 160, "learning_rate": 0.001, "tuner/epochs": 6, "tuner/initial_epoch": 2, "tuner/bracket": 3, "tuner/round": 1, "tuner/trial_id": "0003"}}, "metrics": {"metrics": {"loss": {"direction": "min", "observations": [{"value": [0.6264519095420837], "step": 1}]}, "binary_accuracy": {"direction": "max", "observations": [{"value": [0.6829268336296082], "step": 1}]}, "val_loss": {"direction": "min", "observations": [{"value": [0.4601460099220276], "step": 1}]}, "val_binary_accuracy": {"direction": "max", "observations": [{"value": [0.7804877758026123], "step": 1}]}}}, "score": 0.7804877758026123, "best_step": 1, "status": "COMPLETED", "message": null}